VisageScript/VisageScript.py
VisageScript/VisageScript_tests.py
VisageScript-0.0.1.dist-info/LICENSE
VisageScript-0.0.1.dist-info/METADATA
VisageScript-0.0.1.dist-info/WHEEL
VisageScript-0.0.1.dist-info/entry_points.txt
VisageScript-0.0.1.dist-info/top_level.txt
VisageScript-0.0.1.dist-info/RECORD
