Metadata-Version: 2.1
Name: VisageScript
Version: 0.0.1
Summary: This package contains implementation of VisageScript programming language.
Home-page: https://github.com/PythonApkDev/PythonApkDev.github.io/tree/main/advanced-projects/VisageScript
Author: PythonApkDev
Author-email: pythonapkdev2022@gmail.com
License: MIT
Classifier: Programming Language :: Python :: 3
Classifier: Programming Language :: Python :: 3.7
License-File: LICENSE
